verilog/4_FF_and_Latches/FF_latch.v
module FF_latch(clk,in,data_latch,data_ff);
input clk;
input [3:0] in;
output reg [3:0] data_latch=4'b0;
output reg [3:0] data_ff=4'b0;


//latch code -----input is copied when clk is high
always@(*) begin
   if(clk) begin
      data_latch <= in;
   end
end
//FF code-----input sampled on every clock edge
always@(posedge clk) begin
   data_ff <= in;
end
endmodule

module FF_latch_tb();
reg clk=0;
reg [3:0] in=4'b0;
wire [3:0] data_latch;
wire [3:0] data_ff;



FF_latch uut(clk,in,data_latch,data_ff);
initial begin
  #10
  in = 4'd9;
  #8
  in = 4'd7;
  #20
  in = 4'd9;
  #10
  in = 4'd0;
end

initial begin
   forever #5 clk = ~clk;
end
initial begin #200 $finish; end
initial begin
   $dumpfile("FF_latch.vcd");
   $dumpvars(0,FF_latch_tb);
end


endmodule

verilog/4_FF_and_Latches/FF_latch.vcd
$date
	Sat Feb 22 17:43:48 2025
$end
$version
	Icarus Verilog
$end
$timescale
	1s
$end
$scope module FF_latch_tb $end
$var wire 4 ! data_latch [3:0] $end
$var wire 4 " data_ff [3:0] $end
$var reg 1 # clk $end
$var reg 4 $ in [3:0] $end
$scope module uut $end
$var wire 1 # clk $end
$var wire 4 % in [3:0] $end
$var reg 4 & data_ff [3:0] $end
$var reg 4 ' data_latch [3:0] $end
$upscope $end
$upscope $end
$enddefinitions $end
#0
$dumpvars
b0 '
b0 &
b0 %
b0 $
0#
b0 "
b0 !
$end
#5
1#
#10
0#
b1001 $
b1001 %
#15
b1001 "
b1001 &
b1001 !
b1001 '
1#
#18
b111 !
b111 '
b111 $
b111 %
#20
0#
#25
b111 "
b111 &
1#
#30
0#
#35
1#
#38
b1001 !
b1001 '
b1001 $
b1001 %
#40
0#
#45
b1001 "
b1001 &
1#
#48
b0 !
b0 '
b0 $
b0 %
#50
0#
#55
b0 "
b0 &
1#
