verilog/6_Counters/counter.v
module counter(clk,en,rst,count,ring_counter);

input clk,rst,en;
output reg [3:0] count=0,ring_counter=4'b1000;

always@(posedge clk) begin
  if(rst) begin count <= 4'b0;ring_counter <= 4'b1000; end
  else if(en) begin
    count <= count +1;
    ring_counter <= {ring_counter[0],ring_counter[3:1]};
  end
end
endmodule

module counter_tb();
reg clk=0,en=0,rst=0;
wire [3:0] count,ring_counter;

counter uut(clk,en,rst,count,ring_counter);

initial begin
  #10
  rst=1;
  #10
  rst=0;
  en=1;
  #80
  rst=1;
end

initial begin
   forever #5 clk = ~clk;
end
initial begin #200 $finish; end
initial begin
   $dumpfile("couter.vcd");
   $dumpvars(0,counter_tb);
end



endmodule

verilog/6_Counters/couter.vcd
$date
	Sat Feb 22 18:50:15 2025
$end
$version
	Icarus Verilog
$end
$timescale
	1s
$end
$scope module counter_tb $end
$var wire 4 ! ring_counter [3:0] $end
$var wire 4 " count [3:0] $end
$var reg 1 # clk $end
$var reg 1 $ en $end
$var reg 1 % rst $end
$scope module uut $end
$var wire 1 # clk $end
$var wire 1 $ en $end
$var wire 1 % rst $end
$var reg 4 & count [3:0] $end
$var reg 4 ' ring_counter [3:0] $end
$upscope $end
$upscope $end
$enddefinitions $end
#0
$dumpvars
b1000 '
b0 &
0%
0$
0#
b0 "
b1000 !
$end
#5
1#
#10
0#
1%
#15
1#
#20
0#
1$
0%
#25
b100 !
b100 '
b1 "
b1 &
1#
#30
0#
#35
b10 !
b10 '
b10 "
b10 &
1#
#40
0#
#45
b1 !
b1 '
b11 "
b11 &
1#
#50
0#
#55
b1000 !
b1000 '
b100 "
b100 &
1#
#60
0#
#65
b100 !
b100 '
b101 "
b101 &
1#
#70
0#
#75
b10 !
b10 '
b110 "
b110 &
1#
#80
0#
#85
b1 !
b1 '
b111 "
b111 &
1#
#90
0#
#95
b1000 !
b1000 '
b1000 "
b1000 &
1#
#100
0#
1%
#105
b0 "
b0 &
1#
