verilog/12_FIFO/fifo.v
module fifo(i_rd_en,i_wr_en,i_clk,i_rst,i_wr_data,o_rd_data,o_fifo_full,o_fifo_empty);
input i_clk,i_rst;
input i_rd_en,i_wr_en;
input [7:0] i_wr_data;
output [7:0] o_rd_data;
output o_fifo_full;
output o_fifo_empty;

reg [7:0] mem [0:15]; //16 entries of 8 bits each
reg [7:0] data_out=0;

reg [4:0] wr_ptr_q=0; // adding extra MSB bit to pointer to check if they are in the same iteration or not; to check for full and empty conditions
reg [4:0] rd_ptr_q=0;

wire [4:0] wr_ptr_d,rd_ptr_d;

assign wr_ptr_d = i_wr_en ? wr_ptr_q+1 : wr_ptr_q; //increment or hold
assign rd_ptr_d = i_rd_en ? rd_ptr_q+1 : rd_ptr_q;

always@(posedge i_clk) begin
  if(i_rst) begin
    wr_ptr_q<=0;
  end
  else if(i_wr_en) begin
    wr_ptr_q <= wr_ptr_d;
  end
end
always@(posedge i_clk) begin
  if(i_rst) begin
    rd_ptr_q<=0;
  end
  else if(i_rd_en) begin
    rd_ptr_q <= rd_ptr_d;
  end
end

always@(posedge i_clk) begin
  if(i_wr_en) begin
    mem[wr_ptr_q] <= i_wr_data;
  end
end
always@(posedge i_clk) begin
  if(i_rd_en) begin
    data_out <= mem[rd_ptr_q];
  end
end

assign o_rd_data = data_out;

assign o_fifo_full = wr_ptr_q[3:0] ==rd_ptr_q[3:0] && wr_ptr_q[4]!=rd_ptr_q[4];
assign o_fifo_empty = wr_ptr_q[4:0] ==rd_ptr_q[4:0];    //Beware when Fifo depths are not a power of 2
endmodule

module tb;
reg clk,rst;
reg i_wr_en;
reg i_rd_en;
reg [7:0] i_wr_data;

wire [7:0] o_rd_data;
wire fifo_full;
wire fifo_empty;

initial begin
    rst=1;
    #10
    rst=0;
    clk=0;
    i_wr_en=0;
    i_rd_en=0;
    #10
    i_wr_en=1;
    i_wr_data=8'd4;
    #10
    i_wr_en=0;
    #10
    i_rd_en=1;
    #10
    i_rd_en=0;
    #10
    i_wr_en=1;
    i_wr_data=8'd5;
    #10
    i_wr_data=8'd6;
    #10
    i_wr_data=8'd7;
    #10
    i_wr_data=8'd8;
    #10
    i_wr_data=8'd9;
    #10
    i_wr_data=8'd10;
    #10
    i_wr_data=8'd11;
    #10
    i_wr_data=8'd12;
    #10
    i_wr_data=8'd13;
    #10
    i_wr_data=8'd14;
    #10
    i_wr_data=8'd15;
    #10
    i_wr_data=8'd14;
    #10
    i_wr_data=8'd13;
    #10
    i_wr_data=8'd12;
    #10
    i_wr_data=8'd11;
    #10
    i_wr_data=8'd10;
    #10
    i_wr_data=8'd9;
    #10
    i_wr_data=8'd8;
    #10
    i_wr_data=8'd7;
    #10
    i_wr_en=0;
    #10
    i_rd_en=1;
    #40
    i_rd_en=0;



end

fifo uut(i_rd_en,i_wr_en,clk,rst,i_wr_data,o_rd_data,fifo_full,fifo_empty);
initial begin
   forever #5 clk = ~clk;
end
initial begin #400 $finish; end
initial begin
   $dumpfile("fifo.vcd");
   $dumpvars(0,tb);
end

endmodule

verilog/12_FIFO/fifo.vcd
$date
	Sat May 10 09:23:59 2025
$end
$version
	Icarus Verilog
$end
$timescale
	1s
$end
$scope module tb $end
$var wire 8 ! o_rd_data [7:0] $end
$var wire 1 " fifo_full $end
$var wire 1 # fifo_empty $end
$var reg 1 $ clk $end
$var reg 1 % i_rd_en $end
$var reg 8 & i_wr_data [7:0] $end
$var reg 1 ' i_wr_en $end
$var reg 1 ( rst $end
$scope module uut $end
$var wire 1 $ i_clk $end
$var wire 1 % i_rd_en $end
$var wire 1 ( i_rst $end
$var wire 8 ) i_wr_data [7:0] $end
$var wire 1 ' i_wr_en $end
$var wire 1 " o_fifo_full $end
$var wire 8 * o_rd_data [7:0] $end
$var wire 5 + wr_ptr_d [4:0] $end
$var wire 5 , rd_ptr_d [4:0] $end
$var wire 1 # o_fifo_empty $end
$var reg 8 - data_out [7:0] $end
$var reg 5 . rd_ptr_q [4:0] $end
$var reg 5 / wr_ptr_q [4:0] $end
$upscope $end
$upscope $end
$enddefinitions $end
#0
$dumpvars
b0 /
b0 .
b0 -
b0x ,
b0x +
b0 *
bx )
1(
x'
bx &
x%
x$
1#
0"
b0 !
$end
#10
b0 ,
b0 +
0%
0'
1$
0(
#15
0$
#20
0#
b1 /
b10 +
1$
b100 &
b100 )
1'
#25
0$
#30
b1 +
1$
0'
#35
0$
#40
b100 !
b100 *
b100 -
1#
b1 .
b10 ,
1$
1%
#45
0$
#50
b1 ,
1$
0%
#55
0$
#60
0#
b10 /
b11 +
1$
b101 &
b101 )
1'
#65
0$
#70
b100 +
b11 /
1$
b110 &
b110 )
#75
0$
#80
b101 +
b100 /
1$
b111 &
b111 )
#85
0$
#90
b110 +
b101 /
1$
b1000 &
b1000 )
#95
0$
#100
b111 +
b110 /
1$
b1001 &
b1001 )
#105
0$
#110
b1000 +
b111 /
1$
b1010 &
b1010 )
#115
0$
#120
b1001 +
b1000 /
1$
b1011 &
b1011 )
#125
0$
#130
b1010 +
b1001 /
1$
b1100 &
b1100 )
#135
0$
#140
b1011 +
b1010 /
1$
b1101 &
b1101 )
#145
0$
#150
b1100 +
b1011 /
1$
b1110 &
b1110 )
#155
0$
#160
b1101 +
b1100 /
1$
b1111 &
b1111 )
#165
0$
#170
b1110 +
b1101 /
1$
b1110 &
b1110 )
#175
0$
#180
b1111 +
b1110 /
1$
b1101 &
b1101 )
#185
0$
#190
b10000 +
b1111 /
1$
b1100 &
b1100 )
#195
0$
#200
b10001 +
b10000 /
1$
b1011 &
b1011 )
#205
0$
#210
1"
b10010 +
b10001 /
1$
b1010 &
b1010 )
#215
0$
#220
0"
b10011 +
b10010 /
1$
b1001 &
b1001 )
#225
0$
#230
b10100 +
b10011 /
1$
b1000 &
b1000 )
#235
0$
#240
b10101 +
b10100 /
1$
b111 &
b111 )
#245
0$
#250
b10100 +
1$
0'
#255
0$
#260
b101 !
b101 *
b101 -
b10 .
b11 ,
1$
1%
#265
0$
#270
b100 ,
b11 .
b110 !
b110 *
b110 -
1$
#275
0$
#280
1"
b101 ,
b111 !
b111 *
b111 -
b100 .
1$
#285
0$
#290
0"
b110 ,
b101 .
b1000 !
b1000 *
b1000 -
1$
#295
0$
#300
b101 ,
1$
0%
