verilog/9_Seq_detector/moore_1011_detector.v
module moore_1011_detector(clk,rst,in,out);
input clk,in,rst;
output out;

parameter s0    = 3'b000;
parameter s1    = 3'b001;
parameter s10   = 3'b010;
parameter s101  = 3'b011;
parameter s1011 = 3'b101;


reg [2:0] curr_state,next_state;

always@(posedge clk or posedge rst) begin
  if(rst) curr_state <= s0;
  else curr_state <= next_state;
end

always@(*) begin
case(curr_state)
   s0: begin
          if(in) next_state<=s1;
          else next_state<= s0;
       end
   s1: begin
          if(in) next_state<=s1;
          else next_state<= s10;
       end
   s10: begin
          if(in) next_state<=s101;
          else next_state<= s0;
       end
   s101: begin
          if(in) next_state<=s1011;
          else next_state<= s10;
       end
   s1011: begin
          if(in) next_state<=s1;
          else next_state<= s10;
       end
    default: next_state <= s0;
endcase
end

assign out = (curr_state==s1011)?1:0;//if output is needed in the curr cycle,next_state should be used instead of curr_state
endmodule

module tb;
reg clk=1,in=0,rst=1;
wire out;

moore_1011_detector uut(clk,rst,in,out);
initial begin
   in =0;
   #10
   rst=0;
   in =0;
   #10
   in =1;
   #10
   in =0;
   #10
   in =1;
   #10
   in =0;
   #10
   in =1;
   #10
   in =1;
   #10
   in=0;
end
initial begin
   forever #5 clk = ~clk;
end
initial begin #200 $finish; end
initial begin
   $dumpfile("moore_1011_detector.vcd");
   $dumpvars(0,tb);
end


endmodule

verilog/9_Seq_detector/moore_1011_detector.vcd
$date
	Thu Feb 27 10:13:06 2025
$end
$version
	Icarus Verilog
$end
$timescale
	1s
$end
$scope module tb $end
$var wire 1 ! out $end
$var reg 1 " clk $end
$var reg 1 # in $end
$var reg 1 $ rst $end
$scope module uut $end
$var wire 1 " clk $end
$var wire 1 # in $end
$var wire 1 $ rst $end
$var wire 1 ! out $end
$var reg 3 % curr_state [2:0] $end
$var reg 3 & next_state [2:0] $end
$upscope $end
$upscope $end
$enddefinitions $end
#0
$dumpvars
b0 &
b0 %
1$
0#
1"
0!
$end
#5
0"
#10
1"
0$
#15
0"
#20
b1 &
1"
1#
#25
0"
#30
b1 %
b10 &
1"
0#
#35
0"
#40
b10 %
b11 &
1"
1#
#45
0"
#50
b11 %
b10 &
1"
0#
#55
0"
#60
b10 %
b11 &
1"
1#
#65
0"
#70
b101 &
b11 %
1"
#75
0"
#80
1!
b101 %
b10 &
1"
0#
#85
0"
#90
b0 &
0!
b10 %
1"
#95
0"
#100
b0 %
1"
