verilog/13_Is_mod3/is_mod3.v
module is_mod3(rst,clk,in,out);
input rst,clk;
input in;
output out;

parameter  s0=2'b00;
parameter  s1=2'b01;
parameter  s2=2'b10;


reg [1:0] curr_state,next_state=0;

always@(posedge clk) begin
  if(rst) curr_state <= s0;
  else    curr_state <= next_state;
end


always@(curr_state or in) begin
  next_state = curr_state;  // Default to avoid inferred latches
  if(curr_state==s0) begin
    if(in) next_state = s1;
    else   next_state = s0;
  end
  else if(curr_state==s1) begin
    if(in) next_state = s0;
    else   next_state = s2;
  end
  else if(curr_state==s2) begin
    if(in) next_state = s2;
    else   next_state = s1;
  end
end

assign out = (curr_state==s0 && !rst);
endmodule


module tb;
reg clk,rst,in;
wire out;

initial begin
  rst=1;clk=0;in=0;
  #15 // values to change at posedge
  rst=0;
  #10
  in=1;
  #10
  in=0;
  #10
  in=1;
  #10
  in=0;
  #10
  in=0;
  #10
  in=0;
  #10
  in=1;
  #10
  in=0;


end


is_mod3 uut(rst,clk,in,out);

initial begin
   forever #5 clk = ~clk;
end
initial begin #400 $finish; end
initial begin
   $dumpfile("is_mod3.vcd");
   $dumpvars(0,tb);
end

endmodule

verilog/13_Is_mod3/is_mod3.vcd
$date
	Sat May 10 13:57:16 2025
$end
$version
	Icarus Verilog
$end
$timescale
	1s
$end
$scope module tb $end
$var wire 1 ! out $end
$var reg 1 " clk $end
$var reg 1 # in $end
$var reg 1 $ rst $end
$scope module uut $end
$var wire 1 " clk $end
$var wire 1 # in $end
$var wire 1 ! out $end
$var wire 1 $ rst $end
$var reg 2 % curr_state [1:0] $end
$var reg 2 & next_state [1:0] $end
$upscope $end
$upscope $end
$enddefinitions $end
#0
$dumpvars
bx &
bx %
1$
0#
0"
0!
$end
#5
b0 &
b0 %
1"
#10
0"
#15
1!
1"
0$
#20
0"
#25
0!
b1 %
b0 &
1"
1#
#30
0"
#35
b10 %
b1 &
1"
0#
#40
0"
#45
b10 &
1"
1#
#50
0"
#55
b1 %
b10 &
1"
0#
#60
0"
#65
b1 &
b10 %
1"
#70
0"
#75
b10 &
b1 %
1"
#80
0"
#85
1!
b0 %
b1 &
1"
1#
#90
0"
#95
b0 &
1"
0#
